pysunspec-2.1.1.data/scripts/suns.py
sunspec/__init__.py
sunspec/core/__init__.py
sunspec/core/client.py
sunspec/core/data.py
sunspec/core/device.py
sunspec/core/pics.py
sunspec/core/smdx.py
sunspec/core/suns.py
sunspec/core/util.py
sunspec/core/modbus/__init__.py
sunspec/core/modbus/client.py
sunspec/core/modbus/mbmap.py
sunspec/core/test/__init__.py
sunspec/core/test/test_all.py
sunspec/core/test/test_client.py
sunspec/core/test/test_data.py
sunspec/core/test/test_device.py
sunspec/core/test/test_modbus_client.py
sunspec/core/test/test_modbus_mbmap.py
sunspec/core/test/test_util.py
sunspec/core/test/devices/mbmap_test_device_1.xml
sunspec/core/test/devices/mbmap_test_device_1_a.xml
sunspec/core/test/devices/mbmap_test_device_1_b.xml
sunspec/core/test/devices/mbmap_test_device_1_c.xml
sunspec/core/test/devices/mbmap_test_device_1_d.xml
sunspec/core/test/devices/mbmap_test_device_1_processed.xml
sunspec/core/test/devices/mbmap_test_device_2.xml
sunspec/core/test/devices/mbmap_test_device_3.xml
sunspec/core/test/devices/mbmap_test_inverter_1.xml
sunspec/core/test/devices/mbmap_test_inverter_2.xml
sunspec/core/test/devices/mbmap_test_inverter_3.xml
sunspec/core/test/devices/pics_test_device_1.xml
sunspec/core/test/devices/pics_test_device_2.xml
sunspec/core/test/devices/pics_test_inverter_1.xml
sunspec/core/test/devices/pics_test_inverter_2.xml
sunspec/core/test/fake/__init__.py
sunspec/core/test/fake/serial.py
sunspec/core/test/fake/socket.py
sunspec/models/smdx/CHANGELOG
sunspec/models/smdx/Makefile
sunspec/models/smdx/manifest.py
sunspec/models/smdx/manifest.xml
sunspec/models/smdx/manifest.xml.md5
sunspec/models/smdx/smdx.xsd
sunspec/models/smdx/smdx_00001.xml
sunspec/models/smdx/smdx_00002.xml
sunspec/models/smdx/smdx_00003.xml
sunspec/models/smdx/smdx_00004.xml
sunspec/models/smdx/smdx_00005.xml
sunspec/models/smdx/smdx_00006.xml
sunspec/models/smdx/smdx_00007.xml
sunspec/models/smdx/smdx_00008.xml
sunspec/models/smdx/smdx_00009.xml
pysunspec-2.1.1.dist-info/LICENSE
pysunspec-2.1.1.dist-info/METADATA
pysunspec-2.1.1.dist-info/WHEEL
pysunspec-2.1.1.dist-info/top_level.txt
pysunspec-2.1.1.dist-info/RECORD
