Metadata-Version: 2.1
Name: pysunspec
Version: 2.1.1
Summary: Python SunSpec Tools
Home-page: UNKNOWN
Author: Bob Fox
Author-email: bob@sunspec.org
License: UNKNOWN
Platform: UNKNOWN
Classifier: Operating System :: OS Independent
Classifier: Operating System :: POSIX :: Linux
Classifier: Operating System :: MacOS :: MacOS X
Classifier: Operating System :: Microsoft :: Windows
Classifier: Programming Language :: Python
Classifier: Programming Language :: Python :: 2
Classifier: Programming Language :: Python :: 2.7
Classifier: Programming Language :: Python :: 3
Classifier: Programming Language :: Python :: 3.5
Classifier: Programming Language :: Python :: 3.6
Classifier: Programming Language :: Python :: 3.7
Classifier: Programming Language :: Python :: 3.8
Requires-Python: >=2.7,!=3.0.*,!=3.1.*,!=3.2.*,!=3.3.*,!=3.4.*
Requires-Dist: pyserial
